testcontainers/localstack/__init__.py
tests/test_localstack.py
testcontainers_localstack-0.0.1rc1.dist-info/METADATA
testcontainers_localstack-0.0.1rc1.dist-info/WHEEL
testcontainers_localstack-0.0.1rc1.dist-info/top_level.txt
testcontainers_localstack-0.0.1rc1.dist-info/RECORD
